logwise/__init__.py
logwise/formatter.py
logwise-1.4.0.dist-info/licenses/LICENSE
logwise-1.4.0.dist-info/METADATA
logwise-1.4.0.dist-info/WHEEL
logwise-1.4.0.dist-info/top_level.txt
logwise-1.4.0.dist-info/RECORD
