Metadata-Version: 2.4
Name: logwise
Version: 1.4.0
Summary: A clean, colorful terminal logger with boxed message support.
Home-page: https://github.com/prateekgupta1089/logwise
Author: Prateek Gupta
Author-email: Prateek Gupta <prateekgupta1089@gmail.com>
License: MIT License
Classifier: Programming Language :: Python :: 3
Classifier: License :: OSI Approved :: MIT License
Classifier: Operating System :: OS Independent
Requires-Python: >=3.8
License-File: LICENSE
Requires-Dist: wcwidth>=0.2.6
Dynamic: author
Dynamic: home-page
Dynamic: license-file
Dynamic: requires-python
